MANIFEST.in
README.rst
palette_detect.py
setup.py
palette_detect.egg-info/PKG-INFO
palette_detect.egg-info/SOURCES.txt
palette_detect.egg-info/dependency_links.txt
palette_detect.egg-info/entry_points.txt
palette_detect.egg-info/requires.txt
palette_detect.egg-info/top_level.txt