Metadata-Version: 1.0
Name: palette-detect
Version: 0.2.0
Summary: Palette detection from images.
Home-page: http://bitbucket.org/larsyencken/palette-detect
Author: Lars Yencken
Author-email: lars@yencken.org
License: ISC
Platform: UNKNOWN
